portfolio_simulator/__init__.py
portfolio_simulator/asset.py
portfolio_simulator/mortgage.py
portfolio_simulator/mortgage_test.py
portfolio_simulator/portfolio.py
portfolio_simulator-0.1.8.dist-info/METADATA
portfolio_simulator-0.1.8.dist-info/WHEEL
portfolio_simulator-0.1.8.dist-info/top_level.txt
portfolio_simulator-0.1.8.dist-info/RECORD
