Metadata-Version: 2.1
Name: portfolio-simulator
Version: 0.1.8
Summary: A library that helps you run financial simulations using your financial assets as input.
Home-page: https://github.com/maximehk/portfolio_simulator
Author: Maxime
Author-email: 
License: UNKNOWN
Platform: UNKNOWN
Classifier: Programming Language :: Python :: 3
Classifier: License :: OSI Approved :: MIT License
Classifier: Operating System :: OS Independent
Requires-Python: >=3.6
Requires-Dist: pandas
